articleappkit/__init__.py
articleappkit/admin.py
articleappkit/fields.py
articleappkit/models.py
articleappkit/settings.py
articleappkit/tests.py
articleappkit/views.py
articleappkit/management/__init__.py
articleappkit/management/commands/__init__.py
articleappkit/templates/articlebuilder/placeholder.txt
articleappkit/templatetags/__init__.py
articleappkit/templatetags/articlebuilder_tags.py
django_articleappkit-0.3.dist-info/DESCRIPTION.rst
django_articleappkit-0.3.dist-info/METADATA
django_articleappkit-0.3.dist-info/RECORD
django_articleappkit-0.3.dist-info/WHEEL
django_articleappkit-0.3.dist-info/metadata.json
django_articleappkit-0.3.dist-info/top_level.txt
