Metadata-Version: 2.0
Name: django-articleappkit
Version: 0.3
Summary: A set of classes to make creating text- or article-based Django apps easier.
Home-page: http://callowayproject.com/
Author: Calloway Project
Author-email: webmaster@callowayproject.com
License: UNKNOWN
Platform: UNKNOWN
Classifier: License :: OSI Approved :: Apache Software License
Classifier: Framework :: Django
